ralph/__init__.py
ralph/__main__.py
ralph/cli.py
ralph/commands/__init__.py
ralph/commands/history.py
ralph/commands/init.py
ralph/commands/inspect.py
ralph/commands/reset.py
ralph/commands/run.py
ralph/commands/status.py
ralph/core/__init__.py
ralph/core/agent.py
ralph/core/ignore.py
ralph/core/loop.py
ralph/core/pool.py
ralph/core/prompt.py
ralph/core/run_state.py
ralph/core/snapshot.py
ralph/core/state.py
ralph/output/__init__.py
ralph/output/about.py
ralph/output/colors.py
ralph/output/console.py
ralph_loop-0.3.0.dist-info/METADATA
ralph_loop-0.3.0.dist-info/WHEEL
ralph_loop-0.3.0.dist-info/entry_points.txt
ralph_loop-0.3.0.dist-info/licenses/LICENSE
ralph_loop-0.3.0.dist-info/RECORD
